{
	"stfFile":"npc_reaction/droid_slang",
	"entries": {
		"hit_target_16":"Yer doomed. Why dontcha surrender?",		"hit_target_15":"Ooh, that must 'ave hurt ye.",		"hit_target_14":"Ya better run away while ya can!",		"hit_target_13":"My turn now...!",		"hit_target_12":"Mmmm, lemme see.",		"hit_target_11":"Oh no, ya don't!",		"hit_target_10":"Yer goin' down!",		"hit_target_9":"I got yer!",		"hit_target_8":"C'mere, coward!",		"hit_target_7":"Looks like yer hurt.",		"hit_target_6":"Fight! I love a fight!",		"hit_target_5":"Ha ha! I gotcha!",		"hit_target_4":"You got an ouchie!",		"hit_target_3":"Got ya!",		"hit_target_2":"Hee hee!",		"hit_target_1":"Take that, buddy!",		"ally_16":"Lemme even up the odds summat.",		"ally_15":"Are y'okay, buddy? Lemme take care o' this.",		"ally_14":"Hey now!",		"ally_13":"I don' care who y'are, ya don't touch my friends.",		"ally_12":"Hey now! You should be leavin' my friend alone!",		"ally_11":"Hey! Yer OK?",		"ally_10":"Welp, guess I should be steppin' in here.",		"ally_9":"Yer lookin' like you could use some help.",		"ally_8":"You needin' help here, friend?",		"ally_7":"Pick on a droid yer own size!",		"ally_6":"Coward, why dontcha pick on me instead?",		"ally_5":"Just a sec there! What're ya doin'?",		"ally_4":"Hey now! Back off!",		"ally_3":"Why you little...",		"ally_2":"Ya don' lay a finger on my friends!",		"ally_1":"Get away from my friend there!",		"help_16":"I could be usin' help here!",		"help_15":"Hurry! Over hereabouts!",		"help_14":"Over hereabouts, hurry up now!",		"help_13":"Quick now, over here!",		"help_12":"Argh! Help!",		"help_11":"Hurry, I'm needin' help!",		"help_10":"Uh, can anyone help me?",		"help_9":"Help? Please?",		"help_8":"Ta me! Help!",		"help_7":"I can't handle it all by my lonesome...!",		"help_6":"I could be usin' some help here...!",		"help_5":"Don' mean to bother ya, but... HELP!",		"help_4":"Hellllp!",		"help_3":"Help me!",		"help_2":"I'm needin' some help, anytime now...",		"help_1":"Help!",		"attacked_16":"Here's hopin' yer will is ready.",		"attacked_14":"Aww, don' make me kill ya!",		"attacked_13":"Pickin' on little ol' me, huh?",		"attacked_12":"If'n ya start runnin' now, ya might get away...",		"attacked_11":"'S a good day to die.",		"attacked_10":"Do we have ta fight?",		"attacked_9":"Oohh, I'm SOOOO scared. Heh.",		"attacked_8":"Ya better run. Killin' don't take me long.",		"attacked_7":"They got a table ready for ya in the afterlife, I hear.",		"attacked_6":"Can't wait ta loot yer corpse!",		"attacked_5":"I allus thought I might get dismantled someday.",		"attacked_4":"Ya realize you'll miss out on old age, right?",		"attacked_3":"Another fight? Yeesh, next time I'm invited ta one, I'm skippin'.",		"attacked_2":"Yer not the toughest to try to take me down, ya know.",		"attacked_1":"Flee, or yer gonna die...!",		"hit_16":"Why, you little...",		"hit_15":"Not good, not good...",		"hit_14":"Yer barely scratchin' me!",		"hit_13":"Owie.",		"hit_12":"Hey, is there a mechanic in the house?",		"hit_11":"Hurm, this could be gettin' bad by and by.",		"hit_10":"Ungh!",		"hit_9":"Go on then, try an' do that again!",		"hit_8":"That the best ya can do?",		"hit_7":"Nice try, buddy, but I'm still here!",		"hit_6":"Gee, now yer makin' me mad.",		"hit_5":"Ouch.",		"hit_4":"Agh!",		"hit_3":"You'll need more'n that ta take me down!",		"hit_2":"Jest a scratch.",		"hit_1":"Ow!",		"gloat_16":"An' another one down...",		"gloat_15":"Ya poor dolt...",		"gloat_14":"Good riddance to ya.",		"gloat_13":"Whammo!",		"gloat_12":"Hee hee.",		"gloat_11":"I hate havin' ta kill folks...",		"gloat_10":"Sorry 'bout that.",		"gloat_9":"Next time, bring lotsa friends.",		"gloat_8":"Well, that was sorta pathetic.",		"gloat_7":"Someone better mop this mess up.",		"gloat_6":"Heh, yer thinkin' ya can take ME on?",		"gloat_5":"Now, ya were a worthy opponent and all...",		"gloat_4":"So much fer that.",		"gloat_3":"Whew, that was a close 'un.",		"gloat_2":"Good fight. Yeah.",		"gloat_1":"Well, that was easy, I'm thinkin'.",		"death_16":"Curses, ya broke me!",		"death_15":"FATAL:: dumping core.",		"death_14":"Yer gonna live ta regret this...",		"death_13":"I always thought I'd have more time in this world...",		"death_12":"I... I'm done fer.",		"death_11":"NOOOooooo....",		"death_10":"Urk.",		"death_9":"Yer never goin' ta be rid o' me...",		"death_8":"I swear I'll haunt ya to yer grave...",		"death_7":"I... ain't... agh.",		"death_6":"FATAL:: central core overheated. Memory core crashing.",		"death_5":"I's too newly manufactured ta die.",		"death_4":"Uggg... I'm thinkin' I'm broke.",		"death_3":"AGH! *fzzt*",		"death_2":"My sensors are fadin'... I'm seein' a white tunnel...",		"death_1":"Welp, THAT hurt. Fatal, possibly. Yep.",		"threat_16":"Goody, someone ta practice targets on.",		"threat_15":"Yer better back off, I'm the fastest droid in the system.",		"threat_14":"Yer guts are gonna get spilled on the ground here...",		"threat_13":"Gimme an excuse ta kill ya...",		"threat_12":"Come closer, ya can have a droid beatcha up!",		"threat_11":"Ya wanna taste o' this?",		"threat_10":"I'm thinkin' you'd make a nice stuffed trophy.",		"threat_9":"I'm drawin' a line in the sand here, and I'm on this side, see, and yer on the other side, and... oh, never mind.",		"threat_8":"Ya feelin' lucky? Hmm?",		"threat_7":"C'mon then. Bring it on, buddy!",		"threat_6":"Back off, buddy, or I'll do somethin' yer gonna hate...",		"threat_5":"If ya know what's good for ya, you'll scram on outta here.",		"threat_4":"This is a dangerous place for the likes o' you.",		"threat_3":"Ya better clear on outta here.",		"threat_2":"I don' like yer kind.",		"threat_1":"Take a hike.",		"bye_mean_16":"Glad to have wasted th' time o'day on ya.",		"bye_mean_15":"'Bout time ya got gone, buddy.",		"bye_mean_14":"Next time ya come, bring friends. Love to beat ya ALL up.",		"bye_mean_13":"Here's hopin' ya don't come back!",		"bye_mean_12":"Now that the stink's gone...",		"bye_mean_11":"Better not let me catch ya in a dark alley.",		"bye_mean_10":"Aww, leavin' before a fight huh?",		"bye_mean_9":"No need to run, we can play some, if ya want, heh heh.",		"bye_mean_8":"Overstayed yer welcome, eh?",		"bye_mean_7":"Ya ain't welcome, so get outta here.",		"bye_mean_6":"Better leave, afore I delete ya..",		"bye_mean_5":"Bye bye, scumbag.",		"bye_mean_4":"Thass right, take a hike into a Sarlaac, scumbag.",		"bye_mean_3":"Thass right, walk away, scumbag.",		"bye_mean_2":"Good riddance, buster.",		"bye_mean_1":"Get lost, bud.",		"bye_mid_16":"In a rush, huh? Bye then.",		"bye_mid_15":"Someone waitin' on ya? See ya 'round then.",		"bye_mid_14":"Got a date? See ya later.",		"bye_mid_13":"Gotta go? Bye.",		"bye_mid_12":"Headin' out? Bye.",		"bye_mid_11":"Leavin'? Bye.",		"bye_mid_10":"G'bye now.",		"bye_mid_9":"See ya later.",		"bye_mid_8":"Well now. See ya later.",		"bye_mid_7":"Bye now.",		"bye_mid_6":"See ya 'round.",		"bye_mid_5":"Be seein' ya.",		"bye_mid_4":"See ya.",		"bye_mid_3":"Bye-bye.",		"bye_mid_2":"G'bye.",		"bye_mid_1":"Bye.",		"bye_nice_16":"Don't ferget me, OK?",		"bye_nice_15":"Really great to see ya, y'know.",		"bye_nice_14":"Wuz an honor ter see ya. Honest.",		"bye_nice_13":"Sure hope to see ya again.",		"bye_nice_12":"Will I ever see ya again?",		"bye_nice_11":"Goodbye! Sorry yer headin' out.",		"bye_nice_10":"Yer leavin? Aww...",		"bye_nice_9":"Well, I hate ter see ya go...",		"bye_nice_8":"Aww, you gotta go?",		"bye_nice_7":"Hey now, I'll see ya later!",		"bye_nice_6":"Goodbye, bud!",		"bye_nice_5":"Catch ya later, buddy!",		"bye_nice_4":"I'll see ya 'round!",		"bye_nice_3":"Be seein' ya, buddy!",		"bye_nice_2":"Byebye!",		"bye_nice_1":"Nice ta see ya! Bye now!",		"hi_mean_16":"You like yer bones intact, ya better leave.",		"hi_mean_15":"Well, now, I been itchin' for a fight lately...",		"hi_mean_14":"Y'ain't welcome 'round these parts, scum.",		"hi_mean_13":"Looky here, a maggot come to say hullo.",		"hi_mean_12":"Get yer face outta my sight.",		"hi_mean_11":"Get on outta here.",		"hi_mean_10":"Clear out. You don' wanna see me really angry.",		"hi_mean_9":"Oh brother. What're YOU wantin'?",		"hi_mean_8":"Looky who it is. Lemme plug my ears.",		"hi_mean_7":"What're you snoopin' around for?",		"hi_mean_6":"Oh, 's YOU.",		"hi_mean_5":"Ar now, what're YOU wantin'?",		"hi_mean_4":"Be a waste o' breath to say hullo to the likes of YOU.",		"hi_mean_3":"You smell bantha poodoo? Oh, must be my "friend" here.",		"hi_mean_2":"Looky who's here.",		"hi_mean_1":"Whadda YOU want?",		"hi_mid_16":"Eh?",		"hi_mid_15":"Oh yeah. Can I help ya?",		"hi_mid_14":"Hmm. Yeah?",		"hi_mid_13":"Hmm.",		"hi_mid_12":"Yeah? What's up?",		"hi_mid_11":"Heya.",		"hi_mid_10":"Whatcha want?",		"hi_mid_9":"You lookin' fer someone?",		"hi_mid_8":"You lookin' for summat?",		"hi_mid_7":"Mhhhmmm. Yeah?",		"hi_mid_6":"Hullo.",		"hi_mid_5":"Yeh?",		"hi_mid_4":"Greetin's.",		"hi_mid_3":"Hullo there.",		"hi_mid_2":"Can I help ya?",		"hi_mid_1":"Hullo.",		"hi_nice_16":"Hullo! Yer needin' help?",		"hi_nice_15":"Well, now, looky here! ",		"hi_nice_14":"Sure happy to see ya!",		"hi_nice_13":"Hi there, buddy!",		"hi_nice_12":"Welcome!",		"hi_nice_11":"Hullo! Right nice to see ya!",		"hi_nice_10":"Hey there, buddy!",		"hi_nice_9":"Greetin's, mate!",		"hi_nice_8":"Well, yer a sight for my sore eyes!",		"hi_nice_7":"'S nice to see yer!",		"hi_nice_6":"Well, hullo!",		"hi_nice_5":"Good t'see ya!",		"hi_nice_4":"'S great to see yer!",		"hi_nice_3":"Hullo there!",		"hi_nice_2":"'S wunnerful to see yer again!",		"hi_nice_1":"'S great to see ya again, buddy!",		"flee_16":"Why'm I always in the soup?",		"flee_15":"I don' wanna get diassembled!",		"flee_14":"Time ter run!",		"flee_13":"Time ter get outta hereabouts!",		"flee_12":"Gotta get outta here!",		"flee_11":"Ack no!",		"flee_10":"Hellllp!",		"flee_9":"Time to get outta here!",		"flee_8":"Uh, run for it!",		"flee_7":"Let's get outta here!",		"flee_6":"Run away!",		"calm_16":"Lookin' like the danger's gone.",		"calm_15":"Ho-hum 'n' all that.",		"calm_14":"Well, so much fer that!",		"calm_13":"So much fer that...",		"calm_12":"Golly.",		"calm_11":"Welp, that's that I guess.",		"calm_10":"Welp, that's over.",		"calm_9":"Okeydokey then...!",		"calm_8":"Hmph.",		"calm_7":"No worries, mate!",		"calm_6":"I'm guessin' there's no worries.",		"alert_16":"Now, what'm I hearin'...?",		"alert_15":"Wha...?",		"alert_14":"Oh golly!",		"alert_13":"Now wha...?",		"alert_12":"Uh oh...",		"alert_11":"What the...?",		"alert_10":"Eh now?",		"alert_9":"Hurm?",		"alert_8":"Hang on a bit... what wuzzat?",		"alert_7":"I gots a bad feelin' about this...",		"alert_6":"I'm gettin' a bad feelin' about now...",		"calm_5":"Time ter go to my happy place.",		"calm_4":"Time ter settle down a bit. Whew,",		"calm_3":"I'm thankin' goodness THAT's over.",		"calm_2":"Okeydokey, calmin' down. 'S alright.",		"calm_1":"Whew. Okey, that's done with.",		"flee_5":"Run fer yer lives!",		"flee_4":"Get outta the way! Run!",		"flee_3":"Look out, boys!",		"flee_2":"Help!",		"flee_1":"Oh, by th' stars! Run!",		"alert_5":"Summat's wrong...",		"alert_4":"Wuzzat smell?",		"alert_3":"Didja hear summat?",		"alert_2":"What wuz that?!?",		"alert_1":"Now hold on there...!"
}}
