{
	"stfFile":"spacequest/destroy/c_sink_imp_space",
	"entries": {
		"title_d":"Travel to the Corellia system, hunt down, and destroy five Binayre Black Jacks. You will receive navigational points of common Binayre activity. When you complete this mission, return to Ceth Laike at the Imperial Outpost on Talus.",		"title":"Corellia System: Seek and Destroy 5 Binayre ships.",		"split_quest_alert_fail":"",		"split_quest_alert":"",		"quest_location_t":"Travel to the Corellia System",		"quest_location_d":"The Binayre Pirates tend to hunt in the Corellia system.  Go there to hunt them down.",		"quest_destroy_t":"Destroy 5 Binyare Black Jacks",		"quest_destroy_d":"In an effort to cripple the Binayre Pirates, destroy five of their Black Jacks.",		"autorewardsubject":"",		"autorewardfrom":"",		"autorewardbody":"",		"assigned_delayed":"",		"Quest Log Data":"Text"
}}
