{
	"stfFile":"quest/ground/c_sink_reb",
	"entries": {
		"task10_journal_entry_title":"Mission Complete",		"task10_journal_entry_description":"You completed the mission.",		"task09_journal_entry_title":"Mission Reward",		"task09_journal_entry_description":"You were rewarded for a successful mission.",		"task08_journal_entry_title":"Go into space to kill Hidden Daggers",		"task08_journal_entry_description":"Go into space and await further instructions.",		"task07_journal_entry_title":"Talk to Acun Solari",		"task07_journal_entry_description":"Once you have done as he asked, return to Acun Solari and talk to him.",		"task06_journal_entry_title":"Get 10 Binayre Marks",		"task06_journal_entry_description":"Kill Binayre Pirates on Talus and recover 10 of their gang symbols as proof.  A location to one of their common camps has been added to your datapad.",		"task05_journal_entry_title":"Kill 15 Flails",		"task05_journal_entry_description":"Kill 15 Flails on Corellia.  A location of one of their camps has been added to your datapad.",		"task04_journal_entry_title":"Reward for Returning Alive",		"task04_journal_entry_description":"You have been rewarded with credits and Rebel faction for returning alive with news.",		"task03_journal_entry_title":"Return and Talk to Acun Solari",		"task03_journal_entry_description":"Tell Acun Solari what happened to his friend.",		"task02_journal_entry_title":"ambush (invis)",		"task02_journal_entry_description":"You get ambushed by 4 Flail baddies",		"task01_journal_entry_title":"timer 30-60 seconds (invis)",		"task01_journal_entry_description":"this times an ambush",		"task00_journal_entry_title":"Search and Rescue",		"task00_journal_entry_description":"Go out to a crashed Escape Pod",		"journal_entry_title":"Enough!!",		"journal_entry_description":"After a simple search and rescue mission, Rebel Officer Acun Solari has had enough with the criminal element.",		"category":"Corellia"
}}
