{
	"stfFile":"cmd_ui_d",
	"entries": {
		"cmd_cycletargetsoutwardfriendly":"Cycle Friendly Targets Out",		"cmd_cycletargetsoutwardall":"Cycle All Friend and Enemy Targets Out",		"cmd_cycletargetsinwardfriendly":"Cycle Friendly Targets In",		"cmd_cycletargetsinwardall":"Cycle All Friend and Enemy Targets In",		"cmd_shipthrottledeltaslider":"Throttle Delta (slider) is useful for throttle controls on some gamepads' analog sticks.  If your gamepad analog stick reports as an 'JOYSLIDER', then this is an appropriate command to bind.",		"cmd_shipthrottledeltaaxis":"Throttle Delta (axis) is useful for throttle controls on some gamepads' analog sticks, or on joystick axes.  If your gamepad analog stick reports as an 'JOYAXIS or JOYROT', then this is an appropriate command to bind.",		"cmd_spacetargetstationandcomm":"",		"cmd_spacetargetprevious":"",		"cmd_spacetargetnext":"",		"cmd_targetlock":"Camera Target Lock",		"cmd_rearview":"Camera Rear View",		"cmd_toggleenvironment":"Toggle Environment",		"cmd_spincamera":"Spin Camera",		"cmd_environmentpause":"Environment Pause",		"cmd_swaprollyawaxes":"Swap Roll & Yaw Joystick Axes",		"cmd_uiweapongroupassignment":"",		"cmd_uispacezonemap":"",		"cmd_uispaceassignplayerformation":"",		"cmd_uishipcomponentdetails":"",		"cmd_uiquestjournal":"",		"cmd_uifollowtarget":"",		"cmd_uicomm":"",		"cmd_spacetargetunderreticle":"",		"cmd_spacetargetpreviousonscreenundervariablereticle":"",		"cmd_shiptransfercargo":"",		"cmd_shipthrottlesetslider":"",		"cmd_shipfireandcyclecurrentmissilegroup":"",		"cmd_spacetargetpreviousgroupmember":"",		"cmd_spacetargetpreviousfriendlyplayer":"",		"cmd_spacetargetpreviousfriendly":"",		"cmd_spacetargetpreviousenemyplayer":"",		"cmd_spacetargetpreviousenemy":"",		"cmd_spacetargetnextonscreenundervariablereticle":"",		"cmd_spacetargetnextgroupmember":"",		"cmd_spacetargetnextfriendlyplayer":"",		"cmd_spacetargetnextfriendly":"",		"cmd_spacetargetnextenemyplayer":"",		"cmd_spacetargetnextenemy":"",		"cmd_spacetargetlastenemythatshotplayer":"",		"cmd_spacetargetgroupleader":"",		"cmd_spacetargetclosestship":"",		"cmd_spacetargetclosestplayership":"",		"cmd_spacetargetclosestnpcship":"",		"cmd_spacetargetclosestfriendplayer":"",		"cmd_spacetargetclosestfriend":"",		"cmd_spacetargetclosestenemyplayer":"",		"cmd_spacetargetclosestenemy":"",		"cmd_spacetargetclosestcapship":"",		"cmd_shipthrottlesetsliderm":"",		"cmd_shipthrottlesetaxis":"",		"cmd_shipinspecttarget":"",		"cmd_shipfirecurrentprojectilegroup":"",		"cmd_shipfirecurrentmissilegroup":"",		"cmd_shipfirecountermeasures":"",		"cmd_shipfireandcyclecurrentprojectilegroup":"",		"cmd_shipcyclepreviousprojectilegroup":"",		"cmd_shipcyclepreviousmissilegroup":"",		"cmd_shipcyclenextprojectilegroup":"",		"cmd_shipcyclenextmissilegroup":"",		"cmd_requestspacetrainer":"",		"cmd_leavestation":"",		"cmd_joystickpov":"",		"cmd_escapepod":"",		"cmd_dock":"",		"cmd_run":"Run",		"cmd_shipfireweaponall":"Fire All Weapons",		"cmd_yaw":"Yaw",		"cmd_uiboostertoggle":"Booster",		"cmd_shipyawright":"Yaw Right",		"cmd_shipyawleft":"Yaw Left",		"cmd_shipthrottlefull":"Throttle 100%",		"cmd_shipthrottleset":"Throttle Set",		"cmd_shipthrottlestop":"Throttle 0%",		"cmd_shipthrottledown":"Throttle Decrease",		"cmd_shipthrottleup":"Throttle Increase",		"cmd_shiprollright":"Roll Right",		"cmd_shiprollleft":"Roll Left",		"cmd_shippitchup":"Pitch Up",		"cmd_shippitchdown":"Pitch Down",		"cmd_shipopenclosewings":"Wings Open/Close",		"cmd_shipmatchspeed":"Match Target Speed",		"cmd_shiphyperspacemap":"Hyperspace Map",		"cmd_shipfireweapongroup7":"Fire Weapon Group 8",		"cmd_shipfireweapongroup6":"Fire Weapon Group 7",		"cmd_shipfireweapongroup5":"Fire Weapon Group 6",		"cmd_shipfireweapongroup4":"Fire Weapon Group 5",		"cmd_shipfireweapongroup3":"Fire Weapon Group 4",		"cmd_shipfireweapongroup2":"Fire Weapon Group 3",		"cmd_shipfireweapongroup1":"Fire Weapon Group 2",		"cmd_shipfireweapongroup0":"Fire Weapon Group 1",		"cmd_fireweaponall":"Fire All Weapons",		"cmd_shipfireweapon7":"Fire Weapon 8",		"cmd_shipfireweapon6":"Fire Weapon 7",		"cmd_shipfireweapon5":"Fire Weapon 6",		"cmd_shipfireweapon4":"Fire Weapon 5",		"cmd_shipfireweapon3":"Fire Weapon 4",		"cmd_shipfireweapon2":"Fire Weapon 3",		"cmd_shipfireweapon1":"Fire Weapon 2",		"cmd_shipfireweapon0":"Fire Weapon 1",		"cmd_roll":"Roll",		"cmd_pitch":"Pitch",		"cmd_autopilotlevelship":"Autopilot Level Ship",		"cmd_uicyclecomponenttargetforward":"Cycle Component Target Forward",		"cmd_uicyclecomponenttargetbackward":"Cycle Component Target Backward",		"custom_macro_0001":"Macro 1",		"cmd_examine":"Examine Target",		"cmd_uiholocron":"Holocron",		"cmd_warpplayertofreecamera":"Warp Player to Free Camera",		"cmd_vtuneresume":"VTune Resume",		"cmd_vtunepause":"VTune Pause",		"cmd_vtunecounter":"VTune Counter",		"cmd_uidebugprint":"UI Debug Print",		"cmd_toggleclientenvironment":"Client Environment Toggle",		"cmd_terrainshowlod":"Terrain Show LOD",		"cmd_pause":"Pause",		"cmd_freechasecamera":"Free Chase Camera",		"cmd_freecamera":"Free Camera",		"cmd_fillmode":"Fill Mode",		"cmd_debugportalcamera":"Debug Portal Camera",		"cmd_debugkeycontext2":"Debug Key Context 2",		"cmd_debugkeycontext1":"Debug Key Context 1",		"cmd_clientenvironmentpause":"Client Environment Pause",		"cmd_camerapathplayback":"Camera Path Playback",		"cmd_camerapathnormal":"Camera Path Normal",		"cmd_camerapathdeletelastwaypoint":"Camera Path Delete Last Waypoint",		"cmd_camerapathaddwaypoint":"Camera Path Add Waypoint",		"cmd_uichatroombrowser":"Chat Room Browser",		"cmd_attack":"Attack Target",		"cmd_uitogglechatbubblesminimized":"Chat Bubble Minimize Toggle",		"cmd_panorama":"Panoramic Screenshot",		"cmd_togglerunmomentary":"Momentary Run /Walk Toggle",		"cmd_uitogglehud":"Toggle HUD",		"cmd_console":"Console Toggle",		"cmd_peace":"Stop Fighting (Peace)",		"cmd_clearcombatqueue":"Clear Combat Queue",		"cmd_defaultaction":"Perform Default Action on Target",		"cmd_radialmenu":"Summon Radial Menu",		"cmd_uitoggleobjectnames":"Toggle Object Names",		"cmd_uipointertoggle":"Toggle Mouse Mode",		"cmd_uiconversationstop":"End Conversation",		"cmd_uiconversationstart":"Start Conversation",		"cmd_uiconversationresponse5":"Conversation Response 6",		"cmd_uiconversationresponse4":"Conversation Response 5",		"cmd_uiconversationresponse3":"Conversation Response 4",		"cmd_uiconversationresponse2":"Conversation Response 3",		"cmd_uiconversationresponse1":"Conversation Response 2",		"cmd_uiconversationresponse0":"Conversation Response 1",		"cmd_uicombattarget":"Attack Target",		"cmd_uitoolbarslot23":"Toolbar Bank  2 Slot 12",		"cmd_uitoolbarslot22":"Toolbar Bank  2 Slot 11",		"cmd_uitoolbarslot21":"Toolbar Bank  2 Slot 10 ",		"cmd_uitoolbarslot20":"Toolbar Bank  2 Slot  9",		"cmd_uitoolbarslot19":"Toolbar Bank  2 Slot  8",		"cmd_uitoolbarslot18":"Toolbar Bank  2 Slot  7",		"cmd_uitoolbarslot17":"Toolbar Bank  2 Slot  6",		"cmd_uitoolbarslot16":"Toolbar Bank  2 Slot  5",		"cmd_uitoolbarslot15":"Toolbar Bank  2 Slot  4",		"cmd_uitoolbarslot14":"Toolbar Bank  2 Slot  3",		"cmd_uitoolbarslot13":"Toolbar Bank  2 Slot  2",		"cmd_uitoolbarslot12":"Toolbar Bank  2 Slot  1 ",		"cmd_uitoolbarslot11":"Toolbar Slot 12",		"cmd_uitoolbarslot10":"Toolbar Slot 11",		"cmd_uitoolbarslot09":"Toolbar Slot 10",		"cmd_uitoolbarslot08":"Toolbar Slot  9",		"cmd_uitoolbarslot07":"Toolbar Slot  8",		"cmd_uitoolbarslot06":"Toolbar Slot  7",		"cmd_uitoolbarslot05":"Toolbar Slot  6",		"cmd_uitoolbarslot04":"Toolbar Slot  5",		"cmd_uitoolbarslot03":"Toolbar Slot  4",		"cmd_uitoolbarslot02":"Toolbar Slot  3",		"cmd_uitoolbarslot01":"Toolbar Slot  2",		"cmd_uitoolbarslot00":"Toolbar Slot  1",		"cmd_uitoolbarpane11":"Toolbar Pane 12",		"cmd_uitoolbarpane10":"Toolbar Pane 11",		"cmd_uitoolbarpane09":"Toolbar Pane 10",		"cmd_uitoolbarpane08":"Toolbar Pane  9",		"cmd_uitoolbarpane07":"Toolbar Pane  8",		"cmd_uitoolbarpane06":"Toolbar Pane  7",		"cmd_uitoolbarpane05":"Toolbar Pane  6",		"cmd_uitoolbarpane04":"Toolbar Pane  5",		"cmd_uitoolbarpane03":"Toolbar Pane  4",		"cmd_uitoolbarpane02":"Toolbar Pane  3",		"cmd_uitoolbarpane01":"Toolbar Pane  2",		"cmd_uitoolbarpane00":"Toolbar Pane  1",		"cmd_uitoolbarpaneprev":"Toolbar Pane Previous",		"cmd_uitoolbarpanenext":"Toolbar Pane Next",		"cmd_radarmap":"Radar Map",		"cmd_autorun":"Autorun Toggle",		"cmd_uioptions":"Options",		"cmd_uigamemenuactivate":"Game Menu",		"cmd_chatcopy":"Chat Edit Copy",		"cmd_chatcut":"Chat Edit Cut",		"cmd_chatpaste":"Chat Edit Paste",		"cmd_chatenter":"Chat Enter",		"cmd_chatdelete":"Chat Delete",		"cmd_chatbackspace":"Chat Backspace",		"cmd_chatfontsmaller":"Chat Font Smaller",		"cmd_chatfontbigger":"Chat Font Bigger",		"cmd_chatcommandcompletion":"Chat Command Completion",		"cmd_chathistorydown":"Chat History Next",		"cmd_chathistoryup":"Chat History Previous",		"cmd_chatcursorend":"Chat Cursor End",		"cmd_chatcursorhome":"Chat Cursor Home",		"cmd_chatcursorrightoneword":"Chat Cursor Move Right One Word",		"cmd_chatcursorleftoneword":"Chat Cursor Move Left One Word",		"cmd_chatcursorright":"Chat Cursor Move Right",		"cmd_chatcursorleft":"Chat Cursor Left",		"cmd_uichattabkill":"Kill Chat Tab",		"cmd_uichattabnew":"New Chat Tab",		"cmd_uichattabedit":"Edit Chat Tab",		"cmd_uichattabprev":"Previous Chat Tab",		"cmd_uichattabnext":"Next Chat Tab",		"cmd_uichatbubblesclear":"Chat Bubbles Clear All",		"cmd_uistartchatgroup":"Start Chat Group",		"cmd_uistartchatreply":"Start Chat Reply",		"cmd_uistartchattell":"Start Chat Tell",		"cmd_uistartchatcommand":"Start Chat Command",		"cmd_uistartchat":"Start Chat",		"cmd_screenshot360":"360 Degree Screenshot",		"cmd_camerareset":"Reset Camera Angle",		"cmd_cameralock":"Lock Camera Angle",		"cmd_chasecamera":"Chase Camera Toggle",		"cmd_camerapitchbackward":"Pitch Camera Backward",		"cmd_camerapitchforward":"Pitch Camera Forward",		"cmd_camerayawright":"Yaw Camera Right",		"cmd_camerayawleft":"Yaw Camera Left",		"cmd_camerazoomout":"Zoom Camera Out",		"cmd_camerazoomin":"Zoom Camera In",		"cmd_targetatcursor":"Select Target at Cursor",		"cmd_untarget":"Clear Target",		"cmd_targetgroup9":"Target Group Member 10",		"cmd_targetgroup10":"Target Group Member 11",		"cmd_targetgroup8":"Target Group Member  9",		"cmd_targetgroup7":"Target Group Member  8",		"cmd_targetgroup6":"Target Group Member  7",		"cmd_targetgroup5":"Target Group Member  6",		"cmd_targetgroup4":"Target Group Member  5",		"cmd_targetgroup3":"Target Group Member  4",		"cmd_targetgroup2":"Target Group Member  3",		"cmd_targetgroup1":"Target Group Member  2",		"cmd_targetgroup0":"Target Group Member  1",		"cmd_targetself":"Target Self",		"cmd_uicycletargetgroupprev":"Cycle Target Group Back",		"cmd_uicycletargetgroupnext":"Cycle Target Group Forward",		"cmd_uicycletargetprev":"Cycle Previous Target in History",		"cmd_uicycletargetnext":"Cycle Next Target in History",		"cmd_uicycletargetoutward":"Cycle Target Out",		"cmd_uicycletargetinward":"Cycle Target In",		"cmd_mousewalk":"Walk Toward Cursor",		"cmd_togglelight":"Toggle Light",		"cmd_jump":"Jump",		"cmd_turnright":"Turn Right",		"cmd_turnleft":"Turn Left",		"cmd_right":"Walk Right",		"cmd_down":"Walk Back",		"cmd_left":"Walk Left",		"cmd_walk":"Walk Forward",		"cmd_uiplanetmap":"Planetary Map",		"cmd_uiservice":"knowledge Base Help",		"cmd_postureprone":"Lay Down",		"cmd_posturesit":"Sit Down",		"cmd_posturekneel":"Kneel",		"cmd_posturestand":"Stand Up",		"cmd_uiradarrangeincrease":"Radar Zoom Out",		"cmd_uiradarrangedecrease":"Radar Zoom In",		"cmd_uichatcollapse":"Collapse Chat Box",		"cmd_uicommandbrowser":"Abilities & Commands",		"cmd_uidatapad":"Datapad",		"cmd_uicharactersheet":"Character Sheet",		"cmd_uiinventoryclose":"Inventory",		"cmd_uiskills":"Skills",		"cmd_uipersistentmessagebrowser":"Mail",		"cmd_uicommunity":"Community"
}}
