{
	"stfFile":"corellia_region_names",
	"entries": {
		"corellia_mountain_fortress":"Mountain Fortress PvE Battlefield",		"corellia_rebel_riverside_fort":"Rebel Riverside Fort PvE Battlefield",		"corellia_pvp":"Agrilat Swamp PvP Battlefield",		"loch_khaxus":"Loch Khaxus",		"malal_mountains":"Malal Mountains",		"dregans_pike":"Dregan's Pike",		"suntir_plains":"Suntir Plains",		"riverlands_6":"Riverlands",		"riverlands_5":"Riverlands",		"riverlands_4":"Riverlands",		"riverlands_3":"Riverlands",		"riverlands_2":"Riverlands",		"riverlands_1":"Riverlands",		"bindreg_hills_3":"Bindreg Hills",		"bindreg_hills_2":"Bindreg Hills",		"bindreg_hills_1":"Bindreg Hills",		"rhalers_bastion":"Rhaler's Bastion",		"rier_vem":"Rier'vem",		"rier_let":"Rier'let",		"thaos_mountains_3":"Thaos Mountains",		"thaos_mountains_2":"Thaos Mountains",		"thaos_mountains_1":"Thaos Mountains",		"doaba_guerfel":"Doaba Guerfel",		"vreni_island_1":"Vreni Island",		"denendre_valley_4":"Denendre Valley",		"denendre_valley_3":"Denendre Valley",		"denendre_valley_2":"Denendre Valley",		"denendre_valley_1":"Denendre Valley",		"golden_beaches_8":"Gold Beach",		"golden_beaches_7":"Gold Beach",		"golden_beaches_6":"Gold Beach",		"golden_beaches_5":"Gold Beach",		"golden_beaches_4":"Gold Beach",		"golden_beaches_1":"Gold Beach",		"golden_beaches_2":"Gold Beach",		"golden_beaches_3":"Gold Beach",		"agrilat_swamp_1":"Agrilat Swamp
",		"hard_greater_gulginaw_nw":"Corellia",		"medium_murra_nw":"Corellia",		"medium_slice_hound_nw":"Corellia",		"hard_gronda_nw":"Corellia",		"hard_crimson_sand_panther_sw":"Corellia",		"hard_gulginaw_sw":"Corellia",		"medium_slice_hound_sw":"Corellia",		"hard_gronda_sw":"Corellia",		"medium_sand_panther_se":"Corellia",		"medium_murra_se":"Corellia",		"medium_slice_hound_se":"Corellia",		"medium_dire_cat_se":"Corellia",		"hard_gulginaw_ne":"Corellia",		"medium_plumed_rasp_ne":"Corellia",		"medium_dire_cat_ne":"Corellia",		"hard_gronda_ne":"Corellia",		"southwest_forest":"Corellia",		"western_mountain_forest":"Corellia",		"northwest_forest":"Corellia",		"forest_3":"Corellia",		"forest_2":"Corellia",		"forest_1":"Corellia",		"southeast_mountain_peak":"Corellia",		"southeast_mountain_range":"Corellia",		"northeast_mountains":"Corellia",		"northwest_mountain_peak":"Corellia",		"northwest_mountains":"Corellia",		"northwest_plains":"Corellia",		"north_central_mountains":"Corellia",		"western_plains":"Corellia",		"east_sea_coast":"Corellia",		"southeast_plains":"Corellia",		"agrilat_swamp":"Agrilat Swamp",		"central_plains":"Central Plains",		"vreni_island_medium_newbie":"Corellia",		"doaba_guefel_medium_newbie":"Corellia",		"doaba_guefel_easy_newbie":"Corellia",		"kor_vella_medium_newbie":"Corellia",		"kor_vella_easy_newbie":"Corellia",		"bela_vistal_medium_newbie":"Corellia",		"bela_vistal_easy_newbie":"Corellia",		"tyrena_medium_newbie":"Corellia",		"tyrena_easy_newbie":"Corellia",		"coronet_medium_newbie":"Corellia",		"coronest_easy_newbie":"Corellia",		"world_spawner":"Corellia",		"swamp1":"Corellia",		"forest5":"Corellia",		"forest4":"Corellia",		"forest3":"Corellia",		"forest2":"Corellia",		"forest1":"Corellia",		"lake3":"Corellia",		"lake2":"Corellia",		"lake1":"Corellia",		"beach4":"Corellia",		"beach3":"Corellia",		"beach2":"Corellia",		"beach1":"Corellia",		"grassland8":"Corellia",		"grassland7":"Corellia",		"grassland6":"Corellia",		"grassland5":"Corellia",		"grassland4":"Corellia",		"grassland3":"Corellia",		"grassland2":"Corellia",		"grassland1":"Corellia",		"mountain8":"Corellia",		"mountain7":"Corellia",		"mountain6":"Corellia",		"mountain5":"Corellia",		"mountain4":"Corellia",		"mountain3":"Corellia",		"mountain2":"Corellia",		"mountain1":"Corellia",		"daoba_guerfel":"Doaba Guerfel",		"kor_vella":"Kor Vella",		"vreni_island":"Vreni Island",		"bela_vistal":"Bela Vistal",		"tyrena":"Tyrena",		"coronet":"Coronet"
}}
