{
	"stfFile":"magic_eight_ball",
	"entries": {
		"response50":"Any Sensible Person Would Say They Have No Idea",		"response49":"Any Honest Person Would Say Yes",		"response48":"Any Reasonable Person Would Say No",		"response47":"Look Deep In Your Heart, There The Answer Lies",		"response46":"The Force Is Not With You",		"response45":"The Force Is With You",		"response44":"Cloudy, The Future Is",		"response43":"You Should Ask The Holocron",		"response42":"I Sense You Will Get What You Wish ",		"response41":"I Sense Something Terrible Will Happen ",		"response40":"No, But You Should Keep Trying ",		"response39":"Yes, But Just Barely ",		"response38":"I Think You Overestimate Your Chances ",		"response37":"Make Sure This Is The Right Question ",		"response36":"It Is A Certainty ",		"response35":"A Disturbance In The Force Masks The Future ",		"response34":"In Dark Times, Nothing Is What It Appears To Be ",		"response33":"The Future Is Impossible To See ",		"response32":"No, It Is Not Your Destiny ",		"response31":"Yes, It Is Your Destiny ",		"response30":"Yes, I Have Foreseen It ",		"response29":"I Don't Know, Fly Casual ",		"response28":"Everything Will Proceed As You Have Foreseen ",		"response27":"Difficult To See, The Future Is Always In Motion ",		"response26":"I Have Felt It Is So ",		"response25":"Stretch Out With Your Feelings ",		"response24":"You May Rely On It ",		"response23":"Yes, Definitely ",		"response22":"Yes",		"response21":"Signs Point To Yes ",		"response20":"The Dark Side Clouds Everything, Try Again ",		"response19":"Outlook Not So Good ",		"response18":"Outlook Good ",		"response17":"No",		"response16":"My Reply Is No ",		"response15":"My Reply Is No ",		"response14":"Most Likely ",		"response13":"It Is Certain ",		"response12":"Don't Count On It ",		"response11":"Concentrate And Ask Again ",		"response10":"Better Not Tell You Now ",		"response9":"There Is A Great Disturbance In The Force ",		"response8":"Ask Again Later ",		"response7":"The Future Is Clouded ",		"response6":"Hard To See ",		"response5":"It Looks Pretty Bad ",		"response4":"Trust Your Instincts ",		"response3":"The Outcome Is Not Good ",		"response2":"I Cannot Sense Anything ",		"response1":"I Have A Bad Feeling About This "
}}
